squirro_client/__init__.py
squirro_client/base.py
squirro_client/document_uploader.py
squirro_client/exceptions.py
squirro_client/internal.py
squirro_client/item_uploader.py
squirro_client/user.py
squirro_client/util.py
squirro_client/genai/__init__.py
squirro_client/search/__init__.py
squirro_client/topic/__init__.py
squirro_client/topic/collections.py
squirro_client/topic/communities.py
squirro_client/topic/community_subscription.py
squirro_client/topic/community_types.py
squirro_client/topic/configuration.py
squirro_client/topic/dashboards.py
squirro_client/topic/email_templates.py
squirro_client/topic/enrichments.py
squirro_client/topic/entities.py
squirro_client/topic/facets.py
squirro_client/topic/file_upload.py
squirro_client/topic/globaltemp.py
squirro_client/topic/guidefiles.py
squirro_client/topic/machinelearning.py
squirro_client/topic/ml_candidate_set.py
squirro_client/topic/ml_graphite.py
squirro_client/topic/ml_groundtruth.py
squirro_client/topic/ml_model.py
squirro_client/topic/ml_ner.py
squirro_client/topic/ml_publish.py
squirro_client/topic/ml_sentence_splitter.py
squirro_client/topic/ml_template.py
squirro_client/topic/ml_user_feedback.py
squirro_client/topic/notes.py
squirro_client/topic/objects.py
squirro_client/topic/pipeline_sections.py
squirro_client/topic/pipeline_status.py
squirro_client/topic/pipeline_workflows.py
squirro_client/topic/project_translations.py
squirro_client/topic/projects.py
squirro_client/topic/savedsearches.py
squirro_client/topic/smart_answers.py
squirro_client/topic/sources.py
squirro_client/topic/subscriptions.py
squirro_client/topic/suggest_images.py
squirro_client/topic/synonyms.py
squirro_client/topic/tasks.py
squirro_client/topic/themes.py
squirro_client/topic/widgets_assets.py
squirroclient-3.14.4.dist-info/METADATA
squirroclient-3.14.4.dist-info/WHEEL
squirroclient-3.14.4.dist-info/top_level.txt
squirroclient-3.14.4.dist-info/RECORD
