Metadata-Version: 2.4
Name: SquirroClient
Version: 3.14.4
Summary: Python client for the Squirro API
Home-page: http://dev.squirro.com/docs/tools/python/index.html
Author: Squirro Team
Author-email: support@squirro.com
License: Commercial
Classifier: Development Status :: 5 - Production/Stable
Classifier: Environment :: Web Environment
Classifier: Intended Audience :: Developers
Classifier: License :: Other/Proprietary License
Classifier: Programming Language :: Python :: 3.8
Classifier: Programming Language :: Python :: 3.9
Classifier: Programming Language :: Python :: 3.10
Classifier: Topic :: Internet :: WWW/HTTP
Requires-Python: >=3.6
Requires-Dist: hjson
Requires-Dist: orjson
Requires-Dist: pydantic>2
Requires-Dist: requests<3
Requires-Dist: six
Requires-Dist: tarsafe
Dynamic: author
Dynamic: author-email
Dynamic: classifier
Dynamic: description
Dynamic: home-page
Dynamic: license
Dynamic: requires-dist
Dynamic: requires-python
Dynamic: summary
